update_blacklist/central_repo_updater/__init__.py
update_blacklist/central_repo_updater/clean.py
update_blacklist/central_repo_updater/configuration.py
update_blacklist/central_repo_updater/core.py
update_blacklist/central_repo_updater/deploy.py
update_blacklist/central_repo_updater/generate.py
update_blacklist/central_repo_updater/repositories.py
zlocated_central_repo_updater-1.4.1.dist-info/LICENSE
zlocated_central_repo_updater-1.4.1.dist-info/METADATA
zlocated_central_repo_updater-1.4.1.dist-info/WHEEL
zlocated_central_repo_updater-1.4.1.dist-info/entry_points.txt
zlocated_central_repo_updater-1.4.1.dist-info/top_level.txt
zlocated_central_repo_updater-1.4.1.dist-info/RECORD
